{
    "id": "7870dfdd-e064-421b-95da-59fc2ada6db6",
    "type": "training",
    "app_id": "com.nike.ntc.brand.droid",
    "start_epoch_ms": 1604410006796,
    "end_epoch_ms": 1604410557172,
    "last_modified": 1604410595413,
    "active_duration_ms": 540000,
    "session": false,
    "delete_indicator": false,
    "summaries": [
        {
            "metric": "nikefuel",
            "summary": "mean",
            "source": "nike.ntc.android",
            "app_id": "com.nike.ntc.brand.droid",
            "value": 11.11111111111111
        },
        {
            "metric": "calories",
            "summary": "total",
            "source": "nike.ntc.android",
            "app_id": "com.nike.ntc.brand.droid",
            "value": 20
        },
        {
            "metric": "rpe",
            "summary": "max",
            "source": "nike.ntc.android",
            "app_id": "com.nike.ntc.brand.droid",
            "value": 4
        },
        {
            "metric": "nikefuel",
            "summary": "total",
            "source": "nike.ntc.android",
            "app_id": "com.nike.ntc.brand.droid",
            "value": 100
        }
    ],
    "sources": [
        "nike.ntc.android"
    ],
    "tags": {
        "com_nike_ntc_location": "outside",
        "com_nike_ntc_workout_benchmark": "false",
        "com_nike_ntc_workout_duration_sec": "540",
        "com_nike_ntc_workout_equipment": "none",
        "com_nike_ntc_workout_estimated_calories": "20",
        "com_nike_ntc_workout_focus": "mobility",
        "com_nike_ntc_workout_format": "free",
        "com_nike_ntc_workout_id": "4d422f21-9be2-330a-b137-c2c87b95b51f",
        "com_nike_ntc_workout_intensity": "low",
        "com_nike_ntc_workout_level": "beginner",
        "com_nike_ntc_workout_name": "\u8dd1\u8005\u653e\u677e",
        "com_nike_ntc_workout_seotag": "Nike",
        "com_nike_ntc_workout_type": "time based"
    },
    "change_tokens": [
        "86016ac73b736a3eea3e799cf04885b16bedff77a89facbabac56d6884edb4a3:1604410595413"
    ],
    "metric_types": [
        "rpe",
        "calories",
        "nikefuel"
    ],
    "metrics": [
        {
            "type": "nikefuel",
            "unit": "FUEL",
            "source": "nike.ntc.android",
            "appId": "com.nike.ntc.brand.droid",
            "values": [
                {
                    "start_epoch_ms": 1604410006796,
                    "end_epoch_ms": 1604410557172,
                    "value": 100
                }
            ]
        },
        {
            "type": "rpe",
            "unit": "RATING",
            "source": "nike.ntc.android",
            "appId": "com.nike.ntc.brand.droid",
            "values": [
                {
                    "start_epoch_ms": 1604410006796,
                    "end_epoch_ms": 1604410557172,
                    "value": 4
                }
            ]
        },
        {
            "type": "calories",
            "unit": "KCAL",
            "source": "nike.ntc.android",
            "appId": "com.nike.ntc.brand.droid",
            "values": [
                {
                    "start_epoch_ms": 1604410006796,
                    "end_epoch_ms": 1604410557172,
                    "value": 20
                }
            ]
        }
    ],
    "moments": [
        {
            "key": "drill_complete",
            "value": "799c105b-db58-3287-a981-a12ce6585e3b",
            "timestamp": 1604410046913,
            "app_id": "com.nike.ntc.brand.droid",
            "source": "nike.ntc.android"
        },
        {
            "key": "drill_complete",
            "value": "799c105b-db58-3287-a981-a12ce6585e3b",
            "timestamp": 1604410056983,
            "app_id": "com.nike.ntc.brand.droid",
            "source": "nike.ntc.android"
        },
        {
            "key": "drill_complete",
            "value": "98ba61fc-a40b-3d95-8474-63c050a71bf8",
            "timestamp": 1604410060791,
            "app_id": "com.nike.ntc.brand.droid",
            "source": "nike.ntc.android"
        },
        {
            "key": "drill_complete",
            "value": "799c105b-db58-3287-a981-a12ce6585e3b",
            "timestamp": 1604410086983,
            "app_id": "com.nike.ntc.brand.droid",
            "source": "nike.ntc.android"
        },
        {
            "key": "drill_complete",
            "value": "799c105b-db58-3287-a981-a12ce6585e3b",
            "timestamp": 1604410097017,
            "app_id": "com.nike.ntc.brand.droid",
            "source": "nike.ntc.android"
        },
        {
            "key": "drill_complete",
            "value": "6695ce3e-ab94-3ddc-a9a4-7ca5382ce7b0",
            "timestamp": 1604410105126,
            "app_id": "com.nike.ntc.brand.droid",
            "source": "nike.ntc.android"
        },
        {
            "key": "drill_complete",
            "value": "799c105b-db58-3287-a981-a12ce6585e3b",
            "timestamp": 1604410127016,
            "app_id": "com.nike.ntc.brand.droid",
            "source": "nike.ntc.android"
        },
        {
            "key": "drill_complete",
            "value": "799c105b-db58-3287-a981-a12ce6585e3b",
            "timestamp": 1604410137066,
            "app_id": "com.nike.ntc.brand.droid",
            "source": "nike.ntc.android"
        },
        {
            "key": "drill_complete",
            "value": "2be02713-db22-3e77-a763-c5630ada0f52",
            "timestamp": 1604410138733,
            "app_id": "com.nike.ntc.brand.droid",
            "source": "nike.ntc.android"
        },
        {
            "key": "drill_complete",
            "value": "799c105b-db58-3287-a981-a12ce6585e3b",
            "timestamp": 1604410157066,
            "app_id": "com.nike.ntc.brand.droid",
            "source": "nike.ntc.android"
        },
        {
            "key": "drill_complete",
            "value": "799c105b-db58-3287-a981-a12ce6585e3b",
            "timestamp": 1604410166987,
            "app_id": "com.nike.ntc.brand.droid",
            "source": "nike.ntc.android"
        },
        {
            "key": "drill_complete",
            "value": "4dd7b2d9-5004-3264-b1de-dd8916a71675",
            "timestamp": 1604410175622,
            "app_id": "com.nike.ntc.brand.droid",
            "source": "nike.ntc.android"
        },
        {
            "key": "drill_complete",
            "value": "799c105b-db58-3287-a981-a12ce6585e3b",
            "timestamp": 1604410206987,
            "app_id": "com.nike.ntc.brand.droid",
            "source": "nike.ntc.android"
        },
        {
            "key": "drill_complete",
            "value": "799c105b-db58-3287-a981-a12ce6585e3b",
            "timestamp": 1604410217007,
            "app_id": "com.nike.ntc.brand.droid",
            "source": "nike.ntc.android"
        },
        {
            "key": "drill_complete",
            "value": "d21f9dba-4f64-3780-bd43-40c78f457e5c",
            "timestamp": 1604410229409,
            "app_id": "com.nike.ntc.brand.droid",
            "source": "nike.ntc.android"
        },
        {
            "key": "drill_complete",
            "value": "799c105b-db58-3287-a981-a12ce6585e3b",
            "timestamp": 1604410256998,
            "app_id": "com.nike.ntc.brand.droid",
            "source": "nike.ntc.android"
        },
        {
            "key": "drill_complete",
            "value": "799c105b-db58-3287-a981-a12ce6585e3b",
            "timestamp": 1604410267005,
            "app_id": "com.nike.ntc.brand.droid",
            "source": "nike.ntc.android"
        },
        {
            "key": "drill_complete",
            "value": "6c20b27a-af44-3b56-8798-52067a816491",
            "timestamp": 1604410273930,
            "app_id": "com.nike.ntc.brand.droid",
            "source": "nike.ntc.android"
        },
        {
            "key": "drill_complete",
            "value": "799c105b-db58-3287-a981-a12ce6585e3b",
            "timestamp": 1604410307000,
            "app_id": "com.nike.ntc.brand.droid",
            "source": "nike.ntc.android"
        },
        {
            "key": "drill_complete",
            "value": "799c105b-db58-3287-a981-a12ce6585e3b",
            "timestamp": 1604410317030,
            "app_id": "com.nike.ntc.brand.droid",
            "source": "nike.ntc.android"
        },
        {
            "key": "drill_complete",
            "value": "84cdbf8d-8a65-3c26-83dd-ea4966de2a44",
            "timestamp": 1604410326135,
            "app_id": "com.nike.ntc.brand.droid",
            "source": "nike.ntc.android"
        },
        {
            "key": "drill_complete",
            "value": "799c105b-db58-3287-a981-a12ce6585e3b",
            "timestamp": 1604410357030,
            "app_id": "com.nike.ntc.brand.droid",
            "source": "nike.ntc.android"
        },
        {
            "key": "drill_complete",
            "value": "799c105b-db58-3287-a981-a12ce6585e3b",
            "timestamp": 1604410367154,
            "app_id": "com.nike.ntc.brand.droid",
            "source": "nike.ntc.android"
        },
        {
            "key": "drill_complete",
            "value": "1acfdc2a-c083-323e-873c-71796c207c70",
            "timestamp": 1604410375330,
            "app_id": "com.nike.ntc.brand.droid",
            "source": "nike.ntc.android"
        },
        {
            "key": "drill_complete",
            "value": "799c105b-db58-3287-a981-a12ce6585e3b",
            "timestamp": 1604410407153,
            "app_id": "com.nike.ntc.brand.droid",
            "source": "nike.ntc.android"
        },
        {
            "key": "drill_complete",
            "value": "799c105b-db58-3287-a981-a12ce6585e3b",
            "timestamp": 1604410417163,
            "app_id": "com.nike.ntc.brand.droid",
            "source": "nike.ntc.android"
        },
        {
            "key": "drill_complete",
            "value": "e68b5a74-6e00-3968-934e-5d02498374fb",
            "timestamp": 1604410418277,
            "app_id": "com.nike.ntc.brand.droid",
            "source": "nike.ntc.android"
        },
        {
            "key": "drill_complete",
            "value": "799c105b-db58-3287-a981-a12ce6585e3b",
            "timestamp": 1604410457164,
            "app_id": "com.nike.ntc.brand.droid",
            "source": "nike.ntc.android"
        },
        {
            "key": "drill_complete",
            "value": "799c105b-db58-3287-a981-a12ce6585e3b",
            "timestamp": 1604410467173,
            "app_id": "com.nike.ntc.brand.droid",
            "source": "nike.ntc.android"
        },
        {
            "key": "drill_complete",
            "value": "169a930e-4c6d-33c3-ad35-36036fca9b7b",
            "timestamp": 1604410470192,
            "app_id": "com.nike.ntc.brand.droid",
            "source": "nike.ntc.android"
        },
        {
            "key": "drill_complete",
            "value": "799c105b-db58-3287-a981-a12ce6585e3b",
            "timestamp": 1604410557171,
            "app_id": "com.nike.ntc.brand.droid",
            "source": "nike.ntc.android"
        },
        {
            "key": "drill_start",
            "value": "98ba61fc-a40b-3d95-8474-63c050a71bf8",
            "timestamp": 1604410056983,
            "app_id": "com.nike.ntc.brand.droid",
            "source": "nike.ntc.android"
        },
        {
            "key": "drill_start",
            "value": "799c105b-db58-3287-a981-a12ce6585e3b",
            "timestamp": 1604410060791,
            "app_id": "com.nike.ntc.brand.droid",
            "source": "nike.ntc.android"
        },
        {
            "key": "drill_start",
            "value": "6695ce3e-ab94-3ddc-a9a4-7ca5382ce7b0",
            "timestamp": 1604410097017,
            "app_id": "com.nike.ntc.brand.droid",
            "source": "nike.ntc.android"
        },
        {
            "key": "drill_start",
            "value": "799c105b-db58-3287-a981-a12ce6585e3b",
            "timestamp": 1604410105126,
            "app_id": "com.nike.ntc.brand.droid",
            "source": "nike.ntc.android"
        },
        {
            "key": "drill_start",
            "value": "2be02713-db22-3e77-a763-c5630ada0f52",
            "timestamp": 1604410137066,
            "app_id": "com.nike.ntc.brand.droid",
            "source": "nike.ntc.android"
        },
        {
            "key": "drill_start",
            "value": "799c105b-db58-3287-a981-a12ce6585e3b",
            "timestamp": 1604410138733,
            "app_id": "com.nike.ntc.brand.droid",
            "source": "nike.ntc.android"
        },
        {
            "key": "drill_start",
            "value": "4dd7b2d9-5004-3264-b1de-dd8916a71675",
            "timestamp": 1604410166987,
            "app_id": "com.nike.ntc.brand.droid",
            "source": "nike.ntc.android"
        },
        {
            "key": "drill_start",
            "value": "799c105b-db58-3287-a981-a12ce6585e3b",
            "timestamp": 1604410175622,
            "app_id": "com.nike.ntc.brand.droid",
            "source": "nike.ntc.android"
        },
        {
            "key": "drill_start",
            "value": "d21f9dba-4f64-3780-bd43-40c78f457e5c",
            "timestamp": 1604410217007,
            "app_id": "com.nike.ntc.brand.droid",
            "source": "nike.ntc.android"
        },
        {
            "key": "drill_start",
            "value": "799c105b-db58-3287-a981-a12ce6585e3b",
            "timestamp": 1604410229409,
            "app_id": "com.nike.ntc.brand.droid",
            "source": "nike.ntc.android"
        },
        {
            "key": "drill_start",
            "value": "6c20b27a-af44-3b56-8798-52067a816491",
            "timestamp": 1604410267005,
            "app_id": "com.nike.ntc.brand.droid",
            "source": "nike.ntc.android"
        },
        {
            "key": "drill_start",
            "value": "799c105b-db58-3287-a981-a12ce6585e3b",
            "timestamp": 1604410273930,
            "app_id": "com.nike.ntc.brand.droid",
            "source": "nike.ntc.android"
        },
        {
            "key": "drill_start",
            "value": "84cdbf8d-8a65-3c26-83dd-ea4966de2a44",
            "timestamp": 1604410317030,
            "app_id": "com.nike.ntc.brand.droid",
            "source": "nike.ntc.android"
        },
        {
            "key": "drill_start",
            "value": "799c105b-db58-3287-a981-a12ce6585e3b",
            "timestamp": 1604410326135,
            "app_id": "com.nike.ntc.brand.droid",
            "source": "nike.ntc.android"
        },
        {
            "key": "drill_start",
            "value": "1acfdc2a-c083-323e-873c-71796c207c70",
            "timestamp": 1604410367154,
            "app_id": "com.nike.ntc.brand.droid",
            "source": "nike.ntc.android"
        },
        {
            "key": "drill_start",
            "value": "799c105b-db58-3287-a981-a12ce6585e3b",
            "timestamp": 1604410375330,
            "app_id": "com.nike.ntc.brand.droid",
            "source": "nike.ntc.android"
        },
        {
            "key": "drill_start",
            "value": "e68b5a74-6e00-3968-934e-5d02498374fb",
            "timestamp": 1604410417163,
            "app_id": "com.nike.ntc.brand.droid",
            "source": "nike.ntc.android"
        },
        {
            "key": "drill_start",
            "value": "799c105b-db58-3287-a981-a12ce6585e3b",
            "timestamp": 1604410418278,
            "app_id": "com.nike.ntc.brand.droid",
            "source": "nike.ntc.android"
        },
        {
            "key": "drill_start",
            "value": "169a930e-4c6d-33c3-ad35-36036fca9b7b",
            "timestamp": 1604410467173,
            "app_id": "com.nike.ntc.brand.droid",
            "source": "nike.ntc.android"
        },
        {
            "key": "drill_start",
            "value": "799c105b-db58-3287-a981-a12ce6585e3b",
            "timestamp": 1604410470192,
            "app_id": "com.nike.ntc.brand.droid",
            "source": "nike.ntc.android"
        }
    ]
}